pyslang-stubs/__init__.pyi
pyslang_stubs-9.0.0.20250902.dist-info/WHEEL
pyslang_stubs-9.0.0.20250902.dist-info/METADATA
pyslang_stubs-9.0.0.20250902.dist-info/RECORD
