Metadata-Version: 2.3
Name: pyslang-stubs
Version: 9.0.0.20250902
Summary: Typing stubs for the excellent pyslang library
Author: allRisc
Author-email: allRisc <allrisc.dev@gmail.com>
License:                   GNU LESSER GENERAL PUBLIC LICENSE
Classifier: Programming Language :: Python :: 3
Classifier: Typing :: Stubs Only
Requires-Dist: typing-extensions>=4.15.0
Requires-Python: >=3.9
Project-URL: Homepage, https://github.com/RISCY-Lib/pyslang-stubs
